{
  "type": "request",
  "url": "https://sameday.costco.com/graphql?operationName=VisitShop",
  "method": "POST",
  "headers": {
    "sec-ch-ua-platform": "\"Windows\"",
    "referer": "https://sameday.costco.com/store/costco/products/2577194-ferrero-rocher-chocolates-fine-hazelnut-21-2-oz",
    "sec-ch-ua": "\"Chromium\";v=\"141\", \"Not?A_Brand\";v=\"8\"",
    "sec-ch-ua-mobile": "?0",
    "x-page-view-id": "29d0022e-0ca3-542f-b449-203f5bd280b7",
    "x-client-user-id": "18522876812429916",
    "x-client-identifier": "web",
    "user-agent": "Mozilla/5.0 (Windows NT 10.0; Win64; x64) AppleWebKit/537.36 (KHTML, like Gecko) Chrome/141.0.0.0 Safari/537.36",
    "accept": "*/*",
    "content-type": "application/json"
  },
  "post_data": "{\"operationName\":\"VisitShop\",\"variables\":{\"shopId\":\"6481\",\"postalCode\":\"60181\",\"addressId\":null},\"extensions\":{\"persistedQuery\":{\"version\":1,\"sha256Hash\":\"d2845e5f0022f6d080bf14cd78dbcce9be2a277f12c468e7c43ff0d99a78e77a\"}}}"
}