{
  "type": "response",
  "url": "https://sameday.costco.com/graphql?operationName=DefaultShop&variables=%7B%22postalCode%22%3A%2260181%22%2C%22coordinates%22%3A%7B%22latitude%22%3A41.878643%2C%22longitude%22%3A-87.973518%7D%2C%22addressId%22%3Anull%7D&extensions=%7B%22persistedQuery%22%3A%7B%22version%22%3A1%2C%22sha256Hash%22%3A%22d3ee791a74da13fbeb9f02ba5754725feab0c1c4e5ff795400a0a01b49bedd41%22%7D%7D",
  "status": 200,
  "headers": {
    "x-request-id": "dc1c6352-fe6f-41cb-9b91-46cfdb4d1084",
    "content-encoding": "gzip",
    "etag": "W/\"142b18df813a70018cc946f42b168895\"",
    "x-permitted-cross-domain-policies": "none",
    "x-content-type-options": "nosniff",
    "alt-svc": "h3=\":443\"; ma=86400",
    "server-timing": "runtime;desc=\"Application Runtime\";dur=177, requestId;desc=\"dc1c6352-fe6f-41cb-9b91-46cfdb4d1084\";dur=0",
    "x-cache": "Miss from cloudfront",
    "x-amz-cf-id": "ekkSL7s_E0bPS9_Is_DgldLr17LqU5c8la3tHr_-m4jZIofrG_CqeA==",
    "date": "Thu, 13 Nov 2025 20:26:13 GMT",
    "content-type": "application/json; charset=utf-8",
    "vary": "Accept, Origin",
    "x-runtime": "0.177222",
    "x-frame-options": "SAMEORIGIN",
    "strict-transport-security": "max-age=31536000; includeSubDomains; preload",
    "cache-control": "max-age=0, private, must-revalidate",
    "referrer-policy": "strict-origin-when-cross-origin",
    "x-download-options": "noopen",
    "via": "1.1 d16bc652f24481330d51cba5ea572ca2.cloudfront.net (CloudFront)",
    "x-xss-protection": "1; mode=block",
    "x-amz-cf-pop": "ORD56-P9",
    "server": "nginx"
  },
  "body": "{\"data\": {\"defaultShop\": {\"id\": \"6481\", \"retailerInventorySessionToken\": \"v1.8b68605.18522876812429916-60181-04187x18797-1-5-1091-1-0\", \"retailer\": {\"id\": \"5\", \"categories\": [\"grocery\", \"club\", \"readymeals\", \"gifts\", \"wholesale\"], \"homeCategories\": [\"club\"], \"slug\": \"costco\", \"name\": \"Costco\", \"retailerType\": \"Club/Warehouse Store\", \"backgroundColorHex\": \"#0060a9\", \"refreshHeaderBackgroundColorHex\": \"#0060a9\", \"logoBackgroundColorHex\": \"#ffffff\", \"viewSection\": {\"id\": \"retailers_response_backed:dc6a240c:retailer:5\", \"nameString\": \"Costco Warehouse\", \"retailerCardCategories\": [{\"id\": \"retailers_response_backed:dc6a240c:retailer:5:retailer_card_categories:4a856a1b\", \"categoryString\": \"Groceries\", \"__typename\": \"RetailersResponseBackedRetailerCardCategoriesSection\"}, {\"id\": \"retailers_response_backed:dc6a240c:retailer:5:retailer_card_categories:37bd45d8\", \"categoryString\": \"Wholesale\", \"__typename\": \"RetailersResponseBackedRetailerCardCategoriesSection\"}], \"logoImage\": {\"id\": \"654c732f\", \"altText\": \"Costco logo\", \"templateUrl\": \"https://www.instacart.com/image-server/{width=}x{height=}/www.instacart.com/assets/domains/warehouse/logo/5/65f2304b-908e-4cd0-981d-0d4e4effa8de.png\", \"url\": \"https://www.instacart.com/assets/domains/warehouse/logo/5/65f2304b-908e-4cd0-981d-0d4e4effa8de.png\", \"__typename\": \"Image\"}, \"trackingProperties\": {\"element_details\": {\"element_type\": \"retailer\", \"retailer_details\": {\"retailer_id\": \"5\", \"retailer_type\": \"Club/Warehouse Store\", \"retailer_name\": \"Costco\", \"retailer_slug\": \"costco\"}}}, \"externalUrlString\": null, \"externalRedirectConfirmationHeaderString\": null, \"externalRedirectConfirmationMessageString\": null, \"__typename\": \"RetailersResponseBackedRetailerSection\"}, \"__typename\": \"RetailersRetailer\"}, \"retailerId\": \"5\", \"retailerLocationId\": \"1091\", \"serviceType\": \"delivery\", \"viewSection\": {\"id\": \"retailers_response_backed:d96bc597:shop:6481\", \"trackingProperties\": {\"warehouse_id\": \"5\", \"retailer_id\": \"5\", \"warehouse_id_list\": [\"5\"], \"service_type\": \"delivery\", \"retailer_location_id\": \"1091\"}, \"deliveryString\": \"Delivery\", \"pickupString\": \"\", \"__typename\": \"RetailersResponseBackedShopSection\"}, \"__typename\": \"RetailersShop\"}}}",
  "body_parsed": {
    "data": {
      "defaultShop": {
        "id": "6481",
        "retailerInventorySessionToken": "v1.8b68605.18522876812429916-60181-04187x18797-1-5-1091-1-0",
        "retailer": {
          "id": "5",
          "categories": [
            "grocery",
            "club",
            "readymeals",
            "gifts",
            "wholesale"
          ],
          "homeCategories": [
            "club"
          ],
          "slug": "costco",
          "name": "Costco",
          "retailerType": "Club/Warehouse Store",
          "backgroundColorHex": "#0060a9",
          "refreshHeaderBackgroundColorHex": "#0060a9",
          "logoBackgroundColorHex": "#ffffff",
          "viewSection": {
            "id": "retailers_response_backed:dc6a240c:retailer:5",
            "nameString": "Costco Warehouse",
            "retailerCardCategories": [
              {
                "id": "retailers_response_backed:dc6a240c:retailer:5:retailer_card_categories:4a856a1b",
                "categoryString": "Groceries",
                "__typename": "RetailersResponseBackedRetailerCardCategoriesSection"
              },
              {
                "id": "retailers_response_backed:dc6a240c:retailer:5:retailer_card_categories:37bd45d8",
                "categoryString": "Wholesale",
                "__typename": "RetailersResponseBackedRetailerCardCategoriesSection"
              }
            ],
            "logoImage": {
              "id": "654c732f",
              "altText": "Costco logo",
              "templateUrl": "https://www.instacart.com/image-server/{width=}x{height=}/www.instacart.com/assets/domains/warehouse/logo/5/65f2304b-908e-4cd0-981d-0d4e4effa8de.png",
              "url": "https://www.instacart.com/assets/domains/warehouse/logo/5/65f2304b-908e-4cd0-981d-0d4e4effa8de.png",
              "__typename": "Image"
            },
            "trackingProperties": {
              "element_details": {
                "element_type": "retailer",
                "retailer_details": {
                  "retailer_id": "5",
                  "retailer_type": "Club/Warehouse Store",
                  "retailer_name": "Costco",
                  "retailer_slug": "costco"
                }
              }
            },
            "externalUrlString": null,
            "externalRedirectConfirmationHeaderString": null,
            "externalRedirectConfirmationMessageString": null,
            "__typename": "RetailersResponseBackedRetailerSection"
          },
          "__typename": "RetailersRetailer"
        },
        "retailerId": "5",
        "retailerLocationId": "1091",
        "serviceType": "delivery",
        "viewSection": {
          "id": "retailers_response_backed:d96bc597:shop:6481",
          "trackingProperties": {
            "warehouse_id": "5",
            "retailer_id": "5",
            "warehouse_id_list": [
              "5"
            ],
            "service_type": "delivery",
            "retailer_location_id": "1091"
          },
          "deliveryString": "Delivery",
          "pickupString": "",
          "__typename": "RetailersResponseBackedShopSection"
        },
        "__typename": "RetailersShop"
      }
    }
  }
}