{
  "type": "request",
  "url": "https://sameday.costco.com/graphql?operationName=HomepagePbiRetailerLocality&variables=%7B%22retailerIds%22%3A%5B%225%22%2C%221245%22%2C%221250%22%2C%223204%22%5D%2C%22postalCode%22%3A%2260181%22%2C%22coordinates%22%3A%7B%22latitude%22%3A0%2C%22longitude%22%3A0%7D%7D&extensions=%7B%22persistedQuery%22%3A%7B%22version%22%3A1%2C%22sha256Hash%22%3A%22580af42310a36f0e6d00bd715dc6132695b0a6a90a96c2d5692c6688f71d7d80%22%7D%7D",
  "method": "GET",
  "headers": {
    "sec-ch-ua-platform": "\"Windows\"",
    "referer": "https://sameday.costco.com/",
    "sec-ch-ua": "\"Chromium\";v=\"141\", \"Not?A_Brand\";v=\"8\"",
    "sec-ch-ua-mobile": "?0",
    "x-client-identifier": "web",
    "user-agent": "Mozilla/5.0 (Windows NT 10.0; Win64; x64) AppleWebKit/537.36 (KHTML, like Gecko) Chrome/141.0.0.0 Safari/537.36",
    "accept": "*/*",
    "content-type": "application/json"
  },
  "post_data": ""
}